{
  "rpc_url": "https://evm-t3.cronos.org",
  "private_key": "${DEPLOYER_PRIVATE_KEY}",
  "chain_id": 338,
  "gas_price_gwei": 10,
  "owner_address": "${OWNER_ADDRESS}",
  "fee_collector_address": "${FEE_COLLECTOR_ADDRESS}",
  "fee_percentage": 100,
  "reputation_required": 50,
  "default_stake": 1000000000000000000,
  "wallet_name": "Paygent Agent Wallet",
  "wallet_symbol": "PAW",
  "deploy_vvs_adapter": true,
  "deploy_moonlander_adapter": true,
  "deploy_delphi_adapter": true,
  "vvs_router_address": "0x145677FC4789bFd83a053C29AfE5c5B87c3E2A5B",
  "weth_address": "0x5C7F8A570d558CC2539310C0279Bd69D4FCEE618",
  "vvs_factory_address": "0xf484244E332A1cD0460eF3Fea061c21b9Ec95951",
  "moonlander_router_address": "0xMoonlanderRouter",
  "fee_manager_address": "0xFeeManager",
  "default_leverage": 10,
  "delphi_registry_address": "0xDelphiRegistry",
  "delphi_fee": 500
}